put_back_iterator.py
put_back_iterator-0.1.0a1.dist-info/licenses/LICENSE
put_back_iterator-0.1.0a1.dist-info/METADATA
put_back_iterator-0.1.0a1.dist-info/WHEEL
put_back_iterator-0.1.0a1.dist-info/top_level.txt
put_back_iterator-0.1.0a1.dist-info/RECORD
