Metadata-Version: 2.4
Name: put-back-iterator
Version: 0.1.0a1
Summary: A drop-in replacement for `iter(iterable)` that allows **putting items back** after consuming them. Ideal for parsing, lexing, and other scenarios requiring lookahead or backtracking.
Author-email: Jifeng Wu <jifengwu2k@gmail.com>
License-Expression: MIT
Project-URL: Homepage, https://github.com/jifengwu2k/put-back-iterator
Project-URL: Bug Tracker, https://github.com/jifengwu2k/put-back-iterator/issues
Classifier: Programming Language :: Python :: 2
Classifier: Programming Language :: Python :: 3
Classifier: Operating System :: OS Independent
Requires-Python: >=2
License-File: LICENSE
Requires-Dist: typing; python_version < "3.5"
Dynamic: license-file
